eli/__init__.py
eli/cli.py
eli/constants/__init__.py
eli/constants/informations.py
eli/constants/service.py
eli/constants/system.py
eli/exceptions/__init__.py
eli/exceptions/auth.py
eli/exceptions/connection.py
eli/exceptions/system.py
eli/middlewares/__init__.py
eli/middlewares/mindsdb.py
eli/templates/__init__.py
eli/templates/mindsdb_queries.py
eli_pa-1.0.1.dist-info/LICENSE
eli_pa-1.0.1.dist-info/METADATA
eli_pa-1.0.1.dist-info/WHEEL
eli_pa-1.0.1.dist-info/entry_points.txt
eli_pa-1.0.1.dist-info/top_level.txt
eli_pa-1.0.1.dist-info/RECORD
