Metadata-Version: 2.1
Name: eli-pa
Version: 1.0.1
Summary: Your AI-powered pair personal assistant.
Home-page: https://github.com/AvaterClasher/eli
Author: Soumyadip Moni
Author-email: avater.clasher@gmail.com
License: MIT
Keywords: eli
Classifier: Development Status :: 4 - Beta
Classifier: Intended Audience :: Developers
Classifier: Intended Audience :: Education
Classifier: License :: OSI Approved :: MIT License
Classifier: Natural Language :: English
Classifier: Operating System :: POSIX
Classifier: Operating System :: Unix
Classifier: Operating System :: MacOS
Classifier: Programming Language :: Python :: 3
Classifier: Programming Language :: Python :: 3 :: Only
Classifier: Programming Language :: Python :: Implementation :: CPython
Classifier: Programming Language :: Python :: Implementation :: PyPy
Classifier: Topic :: Utilities
Requires-Python: >=3.7
License-File: LICENSE
Requires-Dist: keyring >=23.13.1
Requires-Dist: mindsdb-sdk >=1.0.2
Requires-Dist: rich >=13.3.4
